pylista/__init__.py
pylista/cli.py
pylista/defaults.py
pylista/lists.py
pylista-0.1.0.dist-info/entry_points.txt
pylista-0.1.0.dist-info/WHEEL
pylista-0.1.0.dist-info/METADATA
pylista-0.1.0.dist-info/RECORD
