Metadata-Version: 2.1
Name: pylista
Version: 0.1.0
Summary: A simple CLI tool to manage lists
Author: Herson Oliveira
Author-email: oliveira.herson@gmail.com
Requires-Python: >=3.8,<4.0
Classifier: Programming Language :: Python :: 3
Classifier: Programming Language :: Python :: 3.8
Classifier: Programming Language :: Python :: 3.9
Requires-Dist: click (>=8.0.1,<9.0.0)
